{
  "document_id": "19720117_105_s1",
  "title": "Pouvoirs de signature de la Tunisie",
  "year": 1972,
  "doc_type": "Pouvoirs",
  "languages": [
    "ar",
    "fr"
  ],
  "quality_score": 0.8576,
  "review_required": true,
  "review_priority": "normal",
  "text_preview": "تفويض وزارة الثرُون المارجيّة باسْم الحكومَة التونسية نحنْ وزير السُؤُون الخاريّة نعيّن بمقتضى هذا السيَّد عبد السلام بن عياد سفير الجمهورية التونستَية بفرنسًا ليوقع باسم الحكومة التوسيّة البروتكول القَاضيئ بتحوبر اتفَاقيَة 22 نوف هبر س8:وانة المتعلقة بالمعارض الدوليَّة . مرر بتونس بة 24 نوفير 1972 واثبانا لذلك أمضينا هذا التفويض عمَّد المصموديئ : 2151 c TRADUCTION NON OFFICIELLE POUVOIRS /)ous Mohamed MASMOUDI, Min…",
  "tags": [
    "century:c20",
    "corpus:traites",
    "doc_type:Pouvoirs",
    "instrument_type:other",
    "legal_force:unknown",
    "period:world_war_ii_and_postwar_1939_1989",
    "rights_status:to_review",
    "source_db:traites_mineae",
    "stage:live_snapshot"
  ],
  "source_url": "https://fr.ftp.opendatasoft.com/mineae/traites/19720117_105_s1.pdf",
  "source_filename": "19720117_105_s1.pdf",
  "source_sha256": "e7e5553bff9fafc4eeb669425451e81ace8c32c22ea188bed6ed9529876edf82",
  "treaty_id": "TRA19720117",
  "treaty_number": "TUN001",
  "rights_status": "to_review",
  "pages": [
    {
      "page_number": 1,
      "text": "تفويض\n\nوزارة الثرُون المارجيّة",
      "quality_score": 0.7357,
      "review_required": true,
      "review_priority": "normal",
      "method": "apple_vision",
      "language": [],
      "review_reasons": [
        "low_confidence",
        "engine_disagreement"
      ]
    },
    {
      "page_number": 2,
      "text": "باسْم الحكومَة التونسية نحنْ وزير السُؤُون الخاريّة نعيّن بمقتضى هذا السيَّد عبد السلام بن عياد سفير الجمهورية التونستَية بفرنسًا ليوقع باسم الحكومة التوسيّة البروتكول القَاضيئ بتحوبر اتفَاقيَة 22 نوف هبر س8:وانة المتعلقة\n\nبالمعارض الدوليَّة .\n\nمرر بتونس بة 24 نوفير 1972\n\nواثبانا لذلك أمضينا هذا التفويض عمَّد المصموديئ\n\n: 2151 c",
      "quality_score": 0.8757,
      "review_required": true,
      "review_priority": "normal",
      "method": "apple_vision",
      "language": [
        "ar"
      ],
      "review_reasons": [
        "engine_disagreement"
      ]
    },
    {
      "page_number": 3,
      "text": "TRADUCTION NON OFFICIELLE\n\nPOUVOIRS\n\n/)ous Mohamed MASMOUDI, Ministro des Affaires\n\nEtrangères de la République Tunisienne désignona par les présents Monsieur Abdessal en BEN AYED, Ambassadear de la\n\nRépublique Tunisienne en France pour signer au nom du\n\nGouvernenent Tunisien le Protocole portant modification de la Convontion du 22 Novembre 1928 sur les Expositions\n\nEn foi de quoi nous signons les présents\n\nFait & Tunis Le 24 Novembre 1972\n\n*° 51",
      "quality_score": 0.9615,
      "review_required": false,
      "review_priority": "none",
      "method": "apple_vision",
      "language": [
        "fr"
      ],
      "review_reasons": []
    }
  ],
  "similar_documents": [
    {
      "document_id": "19720117_47_s1",
      "title": "Pièces dans 19280002",
      "score": 0.392881,
      "type": "weak_link",
      "provisional": false
    },
    {
      "document_id": "19880095_048_s1",
      "title": "Note verbale d'acceptation par la Tunisie de l'amendement",
      "score": 0.386535,
      "type": "weak_link",
      "provisional": false
    },
    {
      "document_id": "19720117_30_s1",
      "title": "Lettre constituant instrument d'adhésion",
      "score": 0.372918,
      "type": "weak_link",
      "provisional": false
    },
    {
      "document_id": "19720117_76_s1",
      "title": "Note verbale d'accompagnement des pouvoirs de signature",
      "score": 0.370464,
      "type": "weak_link",
      "provisional": false
    },
    {
      "document_id": "tra19280002_mex002_s1",
      "title": "Pouvoir remis au chargé d'affaires à Paris pour déposer l'instrument d'adhésion",
      "score": 0.369482,
      "type": "weak_link",
      "provisional": false
    },
    {
      "document_id": "19240003_64_s1",
      "title": "Pouvoirs de signature de la Tunisie",
      "score": 0.369094,
      "type": "weak_link",
      "provisional": false
    },
    {
      "document_id": "19720117_87_s1",
      "title": "Procès verbal de dépôt de l'instrument de ratification de la Roumanie",
      "score": 0.367718,
      "type": "weak_link",
      "provisional": false
    },
    {
      "document_id": "19720117_100_s1",
      "title": "Pouvoirs de signature de la Suisse",
      "score": 0.366167,
      "type": "weak_link",
      "provisional": false
    },
    {
      "document_id": "19660161_61_s1",
      "title": "Pouvoirs de signature de la Tunisie",
      "score": 0.365358,
      "type": "weak_link",
      "provisional": false
    },
    {
      "document_id": "19720117_114_s1",
      "title": "Procès verbal de dépôt de l'instrument de ratification du Venezuela",
      "score": 0.365113,
      "type": "weak_link",
      "provisional": false
    }
  ]
}
