{
  "document_id": "tra18070007_006_s1",
  "title": "Procès-verbal d'échange des instruments",
  "year": 1807,
  "doc_type": "Procès-verbal",
  "languages": [
    "fr"
  ],
  "quality_score": 0.7785,
  "review_required": true,
  "review_priority": "normal",
  "text_preview": "es soussignes sétant reunis pour procedes. à l'échange des roatifications du craités e d'alliance conclu à tontainebleau le tint ena a tot mil-huit-cent jept, entre dautoajerté 1 Empereurs des Francais, i loi d'Italie, protecteur dela Confédération du Shin; encaréajeté le Roi de Dannemaneto, le dit échange a en lieu enla manière accoutumée Pait à Paris le 21 décnite mit-huit cent sept: • de Bac de Greger",
  "tags": [
    "century:c19",
    "corpus:traites",
    "doc_type:Procès-verbal",
    "instrument_type:other",
    "legal_force:unknown",
    "period:revolutionary_napoleonic_1789_1815",
    "rights_status:to_review",
    "source_db:traites_mineae",
    "stage:live_snapshot"
  ],
  "source_url": "https://fr.ftp.opendatasoft.com/mineae/traites/tra18070007_006_s1.pdf",
  "source_filename": "tra18070007_006_s1.pdf",
  "source_sha256": "3d88a833959f532faa41adfe72291c4c90e6a9facc836ca4ffecd9f4e2ec9d2b",
  "treaty_id": "TRA18070007",
  "treaty_number": "006",
  "rights_status": "to_review",
  "pages": [
    {
      "page_number": 1,
      "text": "es soussignes sétant reunis pour procedes.\n\nà l'échange des roatifications du craités e d'alliance conclu à tontainebleau le tint ena a tot mil-huit-cent jept, entre dautoajerté 1 Empereurs des Francais, i loi d'Italie, protecteur dela\n\nConfédération du Shin; encaréajeté le\n\nRoi de Dannemaneto, le dit échange a en lieu enla manière accoutumée\n\nPait à Paris le 21 décnite mit-huit cent sept:\n\n• de Bac\n\nde Greger",
      "quality_score": 0.7785,
      "review_required": true,
      "review_priority": "normal",
      "method": "apple_vision",
      "language": [
        "fr"
      ],
      "review_reasons": [
        "low_confidence",
        "engine_disagreement",
        "possible_handwriting_or_historical_print"
      ]
    }
  ],
  "similar_documents": [
    {
      "document_id": "tra18580012_007_s1",
      "title": "Procès-verbal d'échange des instruments de ratification",
      "score": 0.363033,
      "type": "weak_link",
      "provisional": true
    },
    {
      "document_id": "tra18250001_005_s1",
      "title": "Instrument de ratification bavarois",
      "score": 0.355361,
      "type": "weak_link",
      "provisional": true
    },
    {
      "document_id": "tra18580012_006_s1",
      "title": "Note interne du consulat de France relative à l'instrument de ratification japonais",
      "score": 0.353536,
      "type": "weak_link",
      "provisional": true
    }
  ]
}
