{
  "document_id": "tra19630356_001b_s1",
  "title": "Protocole annexe",
  "year": 1963,
  "doc_type": "Protocole",
  "languages": [
    "fr"
  ],
  "quality_score": 0.9539,
  "review_required": false,
  "review_priority": "none",
  "text_preview": "PROTOCOLE F relatif aux magistrats mis à la disposition de la République Togolaise. PROTOCOLI ANNEXE relatil aux magistrats mis à la disposition de la République Togolaise. Is Gouvernement de la République Française, d'une part, Le Gouvernement de la République Togolaise, d'autre parti, Sont convenus de ce qui suit: Article ler.- L'accorà général sont applicables aux magistrats dans la mesure où il n'J est pas dérog…",
  "tags": [
    "century:c20",
    "corpus:traites",
    "doc_type:Protocole",
    "instrument_type:treaty",
    "legal_force:unknown",
    "period:world_war_ii_and_postwar_1939_1989",
    "rights_status:to_review",
    "source_db:traites_mineae",
    "stage:live_snapshot"
  ],
  "source_url": "https://fr.ftp.opendatasoft.com/mineae/traites/tra19630356_001b_s1.pdf",
  "source_filename": "tra19630356_001b_s1.pdf",
  "source_sha256": "86d929c450918b05bcd739b11f07b98dcdd39ede9b622c608cede06c781b5082",
  "treaty_id": "TRA19630356",
  "treaty_number": "001b",
  "rights_status": "to_review",
  "pages": [
    {
      "page_number": 1,
      "text": "PROTOCOLE\n\nF\n\nrelatif aux magistrats\n\nmis à la disposition de la République Togolaise.",
      "quality_score": 0.9254,
      "review_required": false,
      "review_priority": "none",
      "method": "apple_vision",
      "language": [
        "fr"
      ],
      "review_reasons": []
    },
    {
      "page_number": 2,
      "text": "PROTOCOLI ANNEXE\n\nrelatil aux magistrats mis à la disposition de la République Togolaise.\n\nIs Gouvernement de la République Française, d'une part,\n\nLe Gouvernement de la République Togolaise, d'autre parti,\n\nSont convenus de ce qui suit:\n\nArticle ler.-\n\nL'accorà général sont applicables aux magistrats dans la mesure où il n'J est pas dérogé par les dispositions de la présente annexe.\n\nArticle 20- La République française s'encage à assurer la formation profes- sionnelle des candidats aux fonctions\n\noriginaires de la Répu-\n\nblique togolate. En vae de nommerire dechein d'assurer lo fonctionnement de ses institutions judiciaires,\n\nle Gouvernement de la République française\n\ns'engage à mettre à sa disposition, dans toute la nesure de ses possibilités, les magistrats qui lui seront nécessaires.\n\nAnticle 3.- Sous réserve des stipulations de la présente annexe, les maristrats mis à la disposition de la République togolaise continuent à être régis par les disnositions statutaires qui leur sont propres.\n\nArticle 4.- Les magistrats mis à la disposition de la République togolaise bénéficient de l'indénendance, des immnités, garanties, privilèges, honneurs et prérogatives auxquels peuvent prétendre les magistrats du coros de la magistrature de la République togolaise.\n\nCet Etat protège les magistrats contre les menaces, outrages, injures, diflanations, attaques et contraintes de quelque nature que ce dont ils seraient l'objet dans l'exercice ou à l'occasion de l'exer- cice de leurs fonctione et répare, le cas échéant, le préjudice qui en serait résulté.\n\nIls ne peuvent âtre inquiétés, en aucune manière, pour les déci- sions auxquelles ils participent, pour les propos qu'ils tiennent à l'audience, ni pour les actes relatifs à leurs fonctions.\n\nLeur entrée en fonction est subordonnée à la prestation du serment dans les formes prévues pour les magistrats du coros de la nagis- trature de la République togolaise.\n\nArtiole 5.- Les magistrats mis à la disposition du Gouvernement togolais ne\n\ndans le cas d'une délégatior\n\nà une fonction au moins équivalente à celles qu'ils occupent et sur avie onforme de la Comrission prévue à l'article 8.\n\nArticle 6.- Lorequ'à la suite d'une promotion de grade ou d'une nomination\n\nle magistrat demande il est fait droit d'office ou à ce nouveau groupe.\n\nDans de cas, le Gouvernement de la République française prend toutes dispositions pour assurer le remplacement de ce magistrat avant son départ.\n\nArticle 7e- Sauf s'il s'agit d'un magistrat relevant du statut de la maristrature togolaise ou qui s'y trouve en position de détachenent, un magistrat ne peut se voir confier des fonotions judiciaires lui donnant autorité sur d'oragistrats appartenant & un grade supérieur au sien dans son cadre\n\nArticle 8.- En matière correctionnelle et oriminelle aucune poursuite ne peut être engagée à l'encontre d'un maristrat que\n\nsur avis conforme d'une\n\ncomission composée de deux magistrats du siège désignéspar le Ministre de la Justice togolaise\n\net des deux negistrats français mis à la disposition\n\nde la République togolaise pour occuper les fonations\n\ndu siège les plus\n\nélevées.\n\nLa Commission élit elle-même son Président. En cas de partage des voix, la Commiscion est considérée comme ayant donné un avis défavorable aux poursuites. La Commission se réunit sur convocation du Ministre de la Justice togolaise; l'avis de la Comnission est transmis, le cas échéant, au parquet compétent.\n\nAu cas où des poursuites sont engagées, le Gourerement de la\n\nRépublique francaise est tenu informé et le nagistrat poursuivi du privilège de juridiction prévu par la législation applicable au Togo au moment de l'entrée en vigueur di présent accord.\n\nFait à Paris, le 10 Juillet 1963\n\nPour ie Gouvernement de\n\nLa R publique Française,\n\nMaitrist\n\nPour le Gouvernement de\n\nLa Répus-tque Topolalap,\n\nAyet\n\nThua",
      "quality_score": 0.9824,
      "review_required": false,
      "review_priority": "none",
      "method": "apple_vision",
      "language": [
        "fr"
      ],
      "review_reasons": []
    }
  ],
  "similar_documents": [
    {
      "document_id": "tra19760086_001_s1",
      "title": "Accord",
      "score": 0.668933,
      "type": "weak_link",
      "provisional": false
    },
    {
      "document_id": "tra19740101_001",
      "title": "Convention (ensemble 1 protocole d'application et 4 annexes)",
      "score": 0.40359,
      "type": "semantic_kin",
      "provisional": false
    },
    {
      "document_id": "tra19610160_100",
      "title": "Protocole de signature",
      "score": 0.393868,
      "type": "weak_link",
      "provisional": false
    },
    {
      "document_id": "tra19760093_001_s1",
      "title": "Accord",
      "score": 0.386736,
      "type": "weak_link",
      "provisional": false
    },
    {
      "document_id": "tra19760089_001_s1",
      "title": "Convention",
      "score": 0.38402,
      "type": "weak_link",
      "provisional": false
    },
    {
      "document_id": "19610161_s1",
      "title": "Publication au JO (cf. p. 84 à 88 du pdf joint)",
      "score": 0.383468,
      "type": "weak_link",
      "provisional": false
    },
    {
      "document_id": "tra19580121_001_s1",
      "title": "Convention",
      "score": 0.381439,
      "type": "weak_link",
      "provisional": false
    },
    {
      "document_id": "tra19610286_005_s1",
      "title": "Instrument nigérien (ensemble texte du Traité et de 10 Accords signés le même jour)",
      "score": 0.380074,
      "type": "weak_link",
      "provisional": false
    },
    {
      "document_id": "tra19630356_001a_s1",
      "title": "Accord général",
      "score": 0.378446,
      "type": "weak_link",
      "provisional": true
    },
    {
      "document_id": "tra19600067_001_s1",
      "title": "Convention",
      "score": 0.37704,
      "type": "weak_link",
      "provisional": false
    }
  ]
}
