{
  "document_id": "TRA20192708_001_s1",
  "title": "Déclaration",
  "year": 2019,
  "doc_type": "Déclaration",
  "languages": [
    "bg",
    "fr",
    "mk",
    "ru"
  ],
  "quality_score": 0.9872,
  "review_required": false,
  "review_priority": "none",
  "text_preview": "DECLARATION D'INTENTION SUR LA COOPERATION ENTRE LE MINISTERE DE L'EUROPE ET DES AFFAIRES ETRANGERES DE LA REPUBLIQUE FRANÇAISE ET LE MINISTERE DES AFFAIRES ETRANGERES DE LA REPUBLIQUE DU TADJIKISTAN POUR LA PERIODE 2019-2023 Le Ministre de l'Europe et des Affaires étrangères de la République Française et le Ministre des Affaires étrangères de la République du Tadjikistan ci-après désignés les « signataires », SOUHA…",
  "tags": [
    "century:c21",
    "corpus:traites",
    "doc_type:Déclaration",
    "instrument_type:declaration",
    "legal_force:unknown",
    "period:contemporary_1990_present",
    "rights_status:to_review",
    "source_db:traites_mineae",
    "stage:live_snapshot"
  ],
  "source_url": "https://fr.ftp.opendatasoft.com/mineae/traites/TRA20192708_001_s1.pdf",
  "source_filename": "TRA20192708_001_s1.pdf",
  "source_sha256": "ab3c979bf39fe8a3d963b80545efc5d4152d8d4cf750756cb55057ebf1493073",
  "treaty_id": "TRA20192708",
  "treaty_number": "001",
  "rights_status": "to_review",
  "pages": [
    {
      "page_number": 1,
      "text": "DECLARATION D'INTENTION\n\nSUR LA COOPERATION\n\nENTRE LE MINISTERE DE L'EUROPE ET DES AFFAIRES ETRANGERES DE LA\n\nREPUBLIQUE FRANÇAISE\n\nET\n\nLE MINISTERE DES AFFAIRES ETRANGERES DE LA REPUBLIQUE DU TADJIKISTAN\n\nPOUR LA PERIODE 2019-2023\n\nLe Ministre de l'Europe et des Affaires étrangères de la République Française et le Ministre des Affaires étrangères de la République du Tadjikistan ci-après désignés les « signataires »,\n\nSOUHAITANT renforcer, par leur action conjointe, la coopération entre leurs gouvernements respectifs ;\n\nRECONNAISSANT l'étroit partenariat qui s'était établi entre la France et le Tadjikistan en particulier lors de l'intervention française en Afghanistan, à l'occasion de laquelle les autorités tadjikes avaient mis à disposition de la France certaines installations de l'aéroport de Douchanbé entre 2001 et 2014 (détachement Détair 00.433), en remerciement de quoi la France s'apprête à remettre aux autorités tadjikes une tour de contrôle sur le territoire dudit acroport ;\n\nRAPPELANT que le Tadjikistan est le premier pays de la région avec lequel la France a signé un accord de coopération en matière de sécurité intérieure, accord qui s'inscrit dans les programmes de l'Union européenne et de l'OSCE, en date du 6 décembre 2002 ;\n\nDESIKEUX de renforcer la coopération pratique sur des problématiques nouvelles du monde contemporain, s'appuyant sur le potentiel et d'expertise respectifs de la France et du Tadjikistan ;\n\nSOUCIEUX de profiter mutuellement de ces échanges de vue afin de renforcer le partenariat bilatéral sur la base de la confiance, de connaissances mutuelles, pour répondre conjointement aux défis du monde contemporain ;\n\nREAFFIRMANT leur attachement à renforcer la coopération bilatérale engagée durant les consultations politiques menées depuis le 8 décembre 2016 ;\n\nCONSIDERANT le protocole sur l'établissement des relations diplomatiques entre la France et le\n\nTadjikistan signé le 29 février 1992;\n\nDECLARENT LEUR INTENTION de coopérer selon les modalités suivantes :",
      "quality_score": 1.0,
      "review_required": false,
      "review_priority": "none",
      "method": "apple_vision",
      "language": [
        "fr"
      ],
      "review_reasons": []
    },
    {
      "page_number": 2,
      "text": "1.les signataires souhaitent encourager la coopération et les échanges réciproques, en coordination avec les ministères, organismes de recherche, entreprises et institutions, français et tadjiks, pour favoriser un dialogue de confiance mutuel et visant au partage des expériences et à la promotion de projets d'intérêt mutuel.\n\n2. Les Signataires renouvellent leur attachement aux domaines envisagés pour la coopération comme suit:\n\na.\n\nLes échanges d'informations et d'expériences entre les Signataires.\n\nb.\n\nLa conduite d'échanges de vue sur les pays de la région centrasiatique, c.\n\nLa coopération étroite dans la lutte contre le terrorisme,\n\nLa promotion d'une coopération internationale entre organismes spécialisés sur la radicalisation religieuse, e.\n\nLa promotion de la coopération dans le domaine de la protection de l'environnement,\n\nf. la coopération étroite pour la promotion de l'égalité entre les femmes et les hommes,\n\n5. La promotion des activités des organismes de recherche spécialisés comme l'IFEAC,\n\nh. La promotion de la coopération dans le domaine culturel,\n\ni. La promotion du dialogue dans le domaine du tourisme,\n\nj. La promotion des échanges entre collectivités locales des deux pays.\n\nLes domaines de coopération pourraient être élargis d'un commun accord des Signataires.\n\n3. Les signataires souhaitent développer des échanges réguliers d'informations et de bonnes pratiques entre eux, lors de consultations politiques bilatérales annuelles. Ce dialogue pourra porter, conformément au point 1 de la présente déclaration, sur :\n\na. Des échanges sur les pays de la région centrasiatique, les dynamiques à l'œuvre dans la région, l'ouverture sur le monde, les politiques de voisinage (Afghanistan, Russie, Iran, Chine), les politiques favorisant le climat des affaires,\n\nb. Un dialogue sur la lutte contre le trafic de drogue et le terrorisme permettant d'identifier les besoins et les solutions que les Signataires peuvent s'apporter mutuellement en termes de savoir-faire et de retour d'expérience,\n\nc. Un travail commun sur le phénomène de la radicalisation religieuse, en France et en Asie centrale, une identification des sources, des moyens de gestion du risque, et de lutte contre l'extrémisme religieux,\n\nd. Une promotion commune de la lutte pour la protection de l'environnement par la mise en œuvre de l'Accord de Paris sur le climat, dont la France et le Tadjikistan sont parties comme base d'un dialogue pour identifier les initiatives qui pourront être menées conjointement dans les domaines de la transition écologique et solidaire, des énergies renouvelables, de la gestion des ressources hydriques et du développement durable.\n\ne. La coopération étroite sur la promotion de l'égalité entre les femmes et les hommes, dans le cadre d'un dialogue identifiant les actions à mener de concert pour garantir l'accès à l'éducation des jeunes filles et promouvoir la place des femmes dans la société, dans l'économie, dans les instances représentatives et gouvernementales,\n\nf. La promotion des droits de l'Homme dans la société moderne, et des valeurs fondamentales de liberté d'expression, liberté d'association, liberté de la presse, défendues par les constitutions respectives de la France et du Tadjikistan,\n\n2",
      "quality_score": 1.0,
      "review_required": false,
      "review_priority": "none",
      "method": "apple_vision",
      "language": [
        "fr"
      ],
      "review_reasons": []
    },
    {
      "page_number": 3,
      "text": "g. La promotion du dialogue dans le domaine du tourisme, fort de l'expertise française et du potentiel tadjik, soutenant les initiatives conjointes, telles la négociation d'un accord sur l'aviation civile et l'étude d'ouverture d'un vol entre la France et le Tadjikistan, des échanges d'expertise et de savoir-faire dans le domaine de la restauration, de l'hôtellerie, de l'industrie du tourisme et du domaine des transports (expertise française dans les infrastructures routières, les transports ferroviaires et l'aéronautique),\n\nh. La promotion de la coopération dans le domaine culturel, marquée par l'organisation sur l'exposition consacrée au Tadjikistan au Musée Guimet sous les hauts-patronages des deux présidents de la République, le développement des échanges dans le domaine de l'archéologie, mais aussi dans le domaine de la conservation des objets d'art, le savoir-faire en termes d'expositions et de promotion de la culture.\n\n4. Les signataires entendent créer un groupe de travail bilatéral chargé de la mise en œuvre de ce dialogue de confiance, trois mois après la signature de la présente déclaration, comme suit: les signataires communiqueront le nom des co-présidents qu'ils auront désignés et la composition du groupe de travail par échange de lettre par voie diplomatique. Le Groupe de travail établira un programme de travail annuel pour les échanges bilatéraux. Les sessions du groupe de travail auront lieu de manière alternée dans les deux pays.\n\nLes signataires pourront associer à leur travail, en complément des directions des deux ministères, des institutions publiques, des universités, des centres de recherche spécialisés comme l'IFEAC et son antenne établie à Douchanbé, des organisations non-gouvernementales et des entreprises qui disposeraient d'un savoir-faire et d'une expertise reconnus dans les domaines identifiés au point 1 de la présente déclaration.\n\nFait à Paris, le 8 novembre 2019, en deux exemplaires originaux, chacun en langues française et tadjike.\n\nPOUR LE MINISTRE DE L'EUROPE ET DES\n\nAFFAIRES ETRANGERES DE LA\n\nREPUBLIQUE FRANÇAISE\n\nPOUR LE MINISTERE DES AFFAIRES\n\nETRANGERES DE LA REPUBLIQUE DU\n\nTADJIKISTAN\n\nJean-Baptiste LEMOYNE\n\nSecrétaire d'Etat auprès du Ministre de\n\nT'Europe et des Affaires étrangères\n\nSirojiddin MUHRIDDIN\n\nMinistre des Affaires étrangères de la\n\nRépublique du Tadjikistan\n\n3",
      "quality_score": 1.0,
      "review_required": false,
      "review_priority": "none",
      "method": "apple_vision",
      "language": [
        "fr"
      ],
      "review_reasons": []
    },
    {
      "page_number": 4,
      "text": "ЭЪЛОМИЯ\n\nоид ба нияти ҳамкорӣ байни\n\nВазорати Аврупо ва корҳои хориҷии Ҷумхурии Фаронса ва Вазорати корҳои хориҷии Ҷумҳурии Тоҷикистон\n\nбарои солҳои 2019-2023\n\nВазири Аврупо ва корҳои хориҷии Ҷумҳурии Фаронса ва\n\nВазири корҳои хориҷии Ҷумҳурии Тоҷикистон, ки минбаъд Имзокунандагон номида мешаванд,\n\nБо НИЯТИ таҳким кардан, бо амалҳои мутакобил, ҳамкорӣ байни ҳукуматҳои онҳо;\n\nБо ЭЪТИРОФИ ҳамкории мушобеҳ, ки байни Фаронса ва Точикистон бунёд гардидааст ва хусусан ҳангоми дахолати Фаронса дар Афғонистон, ки дар давоми он Ҳукумати Тоҷикистон ба ихтиёри Фаронса дар фурудгохи шаҳри Душанбе тули солҳои 2001-2014 таҳҷизоти мушаххас дароварда буд (гуруҳи ҳавоӣ Юеајг 00.433), дар навбати худ, бо кирои миннатдорӣ, Фаронса омода аст, қи ба Ҳукумати\n\nТоҷикистон манораи назоратро дар фурудгоҳи номбурда такдим намояд;\n\nБо ТАВАҶҶУҲ ба он, ки Тоҷикистон аввалин кишварест дар минтақа, ки бо\n\nФаронса созишномаи ҳамкорӣ дар соҳаи бехатарии дохилӣ ба имзо расонида буд, ки қисми таркибии Барномаи Иттиҳоди аврупой ва Озмони Амният ва Ҳамкорӣ дар\n\nАврупо (САҲА) аз 6-уми декабри соли 2002 мебошад;\n\nБо МАНЗУРИ таҳкими робитаҳои амалӣ оид ба масъалаҳои ҷадиди ҷаҳони муосир, бо истифодаи иктидор ва тачрибаи мутаносиби Фаронса ва Тоҷикистон:\n\nБо ТАШВИШИ густурдан мутақобилан аз мубодилаҳои афкор бо максади мустаҳкам намудани ҳамкорӣ дар асоси эътимод, донишҳои мутақобил, барои муттафиқ посух гузоштан ба масъалахои ҷаҳони муосир;\n\nБо ИСҲОРИ омодагӣ барои мустаҳкам намудани ҳамкории дуҷониба дар вақти машваратҳои сиёсӣ аз 8-уми декабри соли 2016 оѓоз ёфта буда;\n\nБо ТАВАҶҶӮҲ ба суратмаҷлис оид ба истиқрори муносибатҳои дипломатӣ байни Фаронса ва Тоҷикистон аз 29-уми феврали соли 1992 ба имзо расида шуда;\n\nЭЪЛОМИ НИЯТИ ХУДРО барои ҳамкории оянда ба тарзи зайл изҳор менамоянд:\n\n1. Имзокунандагон изҳори ташвиқи ҳамкорӣ ва мубодилаи мутақобилан ба тавофуки вазоратҳо, муассисаҳои илмӣ ва тадқиқӣ, корхонаҳо ва муассисаҳо, фаронсавӣ ва точикистонӣ, бо максади мусоидат намудан ба муколамаи эътимоди мутақобилан ва табодули тачриба ва пешбурии лоиҳаҳо ба таври тарафайн, мекунанд.",
      "quality_score": 0.9789,
      "review_required": false,
      "review_priority": "none",
      "method": "tesseract:script/Cyrillic:psm3",
      "language": [
        "mk",
        "bg"
      ],
      "review_reasons": []
    },
    {
      "page_number": 5,
      "text": "2. Имзокунандагон мутобиати худро оид ба ҳамкории дуҷониба дар соҳаҳои зерин иброз менамоянд:\n\nа. Мубодилаи иттилоот ва таҷриба байни Имзокунандагон,\n\nЪ. Табодули афкор оид ба кишварҳои минтақаи Осиёи Марказӣ, с. Ҳамкории қавӣ дар мубориза бо терроризм, й. Мусоидат ба ҳамкории байналмиллалӣ байни мақомоти махсус оид ба пешгирии радикалисми динӣ, е. Мусоидат ба ҳамкорӣ дар соҳаи ҳифзи муҳити зист,\n\nҒ# Ҳамкории зич барои таъмини баробарҳуқуқии занону мардон,\n\n5. Густариши фаъолияти ташкилотҳои махсуси тадқиқотӣ, мисли Институти фаронсавии таҳқиқоти Осиёи Марказӣ (ІЕЕАС), һ. Ҳамкорӣ дар соҳаи фарҳанг, і.Пешбурдии муколама дар соҳаи сайёҳӣ,\n\nЈ.Густариши мубодилаи афкор байни мақомотҳои маҳаллии ҳарду кишвар.\n\nСоҳаҳои ҳамкорӣ метавонанд бо розигии Имзокунандагон вусъат дода шаванд.\n\n3. Имзокунандагон изҳор менамоянд, ки рушди мубодилаи мунтазами иттилоот ва тачриба байни ду тарафро, вақти машваратҳои дуҷонибаи сиёсии ҳарсола, инкишоф диханд. Ин муколама метавонад, тибқи банди 1-уми ин эъломия қисматҳои зеринро дарбар гирад:\n\nа. Мубоҳисот оид ба кишварҳои минтақаи Осиёи Марказӣ, ҷараёни фаъолият дар минтақа, ошкорӣ аз ҷаҳон, сиёсатҳои ҳамҷаворӣ (Афғонистон, Русия,\n\nЭрон, Хитой) ва сиёсатҳои мусоид ба муҳити тиҷоратӣ,\n\nБ. Муколама оид ба мубориза бо гардиши ғайриқонунии маводи мухаддир ва терроризм бо мақсади муайян кардани мӯхтоҷот ва тасмимот, ки Имзокунандагон метавонанд мутақобилан, тавассути «ноу-хау» ва табодули таҷрибаю дониш, пешниҳод намоянд, с. Фаъолияти муштарак оид ба зуҳуроти радикалисми динӣ, дар Фаронса ва дар Осиёи Марказӣ, муайян намудани сарманбаъҳо, воситаҳои идоракунии хавфҳо ва мубориза бар зидди экстремизми динӣ, а. Таблиғ кардани мубориза барои ҳифзи муҳити зист тавассути татбиқи\n\nСозишномаи Порис оид ба тағйирёбии иклим, ки Фаронса ва Тоҷикистон узв мебошанд ҳамчун асос барои муколама оид ба муайян кардани ташаббусхое, ки метавонанд мутакобилан дар соҳаҳои гузариши экологӣ ва ҳамбастагӣ, энержиҳои таҷдидпазир, роҳбарии манбаъҳои 06 ва рушди устувор амалӣ кунанд, е. Ҳамкории зич барои мусоидат ба таъмини баробарҳуқуқии занону мардон дар ҷараёни муколама барои муайян намудани самтҳои фаъолияти амалӣ, бо максади кафолати дастрасӣ ба таҳсилоти ҷавондухтарон ва мусоидат барои баланд бардоштани макоми зан дар ҷомеа, дар иқтисодиёт, дар мақомоти намояндагӣ ва хукуматӣ,",
      "quality_score": 0.9666,
      "review_required": false,
      "review_priority": "none",
      "method": "tesseract:script/Cyrillic:psm3",
      "language": [
        "mk",
        "bg",
        "ru"
      ],
      "review_reasons": []
    },
    {
      "page_number": 6,
      "text": "Ғ Мусоидат ба ҳифзи ҳуқуқи инсон дар ҷомеаи муосир ва арзишҳои аслии озодии баён, озодии иттиходияхо, озодии матбуот, ки конститутсияҳои Фаронса ва\n\nТоҷикистон ҳифз менамоянд,\n\n5. Мусоидат ба муколама дар соҳаи сайёҳӣ, такья кардан ба таҷрибаи азими\n\nФаронса ва имконияти Тоҷикистон, дастгирӣ кардани амалиёти муштарак чун гуфтушунидҳо оид ба имзои созишномаи хавопаймоии кишварӣ ва омӯзиши имконияти ташкили парвозҳо байни Фаронса ва Тоҷикистон, ивази тачрибаю дониш дар соҳаи хӯрокворӣ, хизматрасонии меҳмонхонаҳо, сайёҳӣ ва нақлиёт (таҳқиқи фаронсавӣ дар зерсохтхои рох, нақлиёти роҳи оҳан ва ҳавонавардӣ), һ. Мусоидат ба ҳамкорӣ дар соҳаи фарҳанг, ки бо ташкили намоиш бахшида ба Тоҷикистон дар Осорхонаи Гиме бо сарпарастии бевоситаи президентҳои ду ҷумҳури баргузор хоҳад шуд, мунтабеъ гардидааст, рушди мубодила дар соҳаи бостоншиносӣ, ва ончунин дар соҳаи ҳифзи осори санъат, ноу-хау дар робита ба намоишҳо ва рушди фарҳанг.\n\n4. Имзокунандагон нияти таъсис додани гурӯҳи кории дуҷонибаро доранд, ки ин муколамаи эътимоднокро се моҳ пас аз имзои ин эъломия, ба таври зайл татбиқ мекунанд: имзокунандагон ному насаби ҳамраисони таъиншуда ва ҳайати гурӯҳи кориро тариқи табодули нома бо роҳи дипломатӣ ирсол хоҳанд кард. Гурӯҳи корӣ барномаи кории солонаро барои мубодилаи дуҷониба таҳия хоҳад намуд. Ҷаласаҳои гурӯҳи корӣ бонавбат дар ду кишвар баргузор хоҳанд гашт.\n\nИмзокунандагон метавонанд ба фаъолияти худ, ба ғайр аз раёсатҳои ду вазорат, муассисаҳои давлатӣ, донишгоҳҳо, марказҳои тадқикотӣ, чун ІЕЕАС ва филиали он дар Душанбе, ташкилотҳои ғайриҳукуматӣ ва корхонаҳое, ки дорои ноу-хау ва тачрибаи тахқиқӣ дар соҳаҳои муқарраршудаи банди 1-уми ин эъломия мебошанд, ҷалб намоянд.\n\nИн Эъломия дар ш. Париж, 8 ноябри соли 2019 дар ду нусхаи асл, ҳар кадом бо забонҳои фаронсавӣ ва тоҷикӣ ба имзо расонида шуд.\n\nАз ҷониби Аз ҷониби\n\nВазири Аврупо ва корҳои Вазорати корҳои хориҷии хориҷии Ҷумҳурии Фаронса Ҷумҳурии Тоҷикистон\n\n9-4\n\nЖан-Батист Лемуан Сироҷиддин Муҳриддин\n\nКотиби давлатии Вазири Аврупо Вазири корҳои хориҷии ва корҳои хориҷӣ Ҷумҳурии Тоҷикистон",
      "quality_score": 0.9778,
      "review_required": false,
      "review_priority": "none",
      "method": "tesseract:script/Cyrillic:psm3",
      "language": [
        "ru",
        "bg",
        "mk"
      ],
      "review_reasons": []
    }
  ],
  "similar_documents": [
    {
      "document_id": "TRA20192653_001_s1",
      "title": "Déclaration",
      "score": 0.437221,
      "type": "weak_link",
      "provisional": false
    },
    {
      "document_id": "TRA20182428_001",
      "title": "Protocole",
      "score": 0.408359,
      "type": "semantic_kin",
      "provisional": false
    },
    {
      "document_id": "TRA20213110_001a_s1",
      "title": "Accord",
      "score": 0.406133,
      "type": "semantic_kin",
      "provisional": false
    },
    {
      "document_id": "tra19930030_001",
      "title": "Traité",
      "score": 0.400852,
      "type": "semantic_kin",
      "provisional": false
    },
    {
      "document_id": "TRA20192706_001_s1",
      "title": "Déclaration",
      "score": 0.399735,
      "type": "weak_link",
      "provisional": false
    },
    {
      "document_id": "TRA20100145_s1",
      "title": "Accord",
      "score": 0.398427,
      "type": "weak_link",
      "provisional": false
    },
    {
      "document_id": "tra20240010_001_s1",
      "title": "Feuille de route",
      "score": 0.397903,
      "type": "weak_link",
      "provisional": false
    },
    {
      "document_id": "TRA20192701_001_s1",
      "title": "Accord",
      "score": 0.396429,
      "type": "weak_link",
      "provisional": false
    },
    {
      "document_id": "tra20220078_001_s1",
      "title": "Déclaration",
      "score": 0.395717,
      "type": "weak_link",
      "provisional": false
    },
    {
      "document_id": "TRA20182387_001_s1",
      "title": "Protocole d'entente",
      "score": 0.395357,
      "type": "weak_link",
      "provisional": false
    }
  ]
}
